metasklearn/__init__.py
metasklearn/core/__init__.py
metasklearn/core/problem.py
metasklearn/core/search.py
metasklearn/utils/__init__.py
metasklearn/utils/data_handler.py
metasklearn/utils/evaluation.py
metasklearn/utils/scaler.py
metasklearn/utils/validation.py
metasklearn-0.3.0.dist-info/licenses/LICENSE
metasklearn-0.3.0.dist-info/METADATA
metasklearn-0.3.0.dist-info/WHEEL
metasklearn-0.3.0.dist-info/top_level.txt
metasklearn-0.3.0.dist-info/RECORD
